{".class": "MypyFile", "_fullname": "1-simple_pagination", "is_partial_stub_package": false, "is_stub": false, "names": {".class": "SymbolTable", "List": {".class": "SymbolTableNode", "cross_ref": "typing.List", "kind": "Gdef"}, "Server": {".class": "SymbolTableNode", "kind": "Gdef", "node": {".class": "TypeInfo", "_promote": null, "abstract_attributes": [], "bases": ["builtins.object"], "declared_metaclass": null, "defn": {".class": "ClassDef", "fullname": "1-simple_pagination.Server", "name": "Server", "type_vars": []}, "flags": [], "fullname": "1-simple_pagination.Server", "metaclass_type": null, "metadata": {}, "module_name": "1-simple_pagination", "mro": ["1-simple_pagination.Server", "builtins.object"], "names": {".class": "SymbolTable", "DATA_FILE": {".class": "SymbolTableNode", "kind": "Mdef", "node": {".class": "Var", "flags": ["is_initialized_in_class", "is_ready"], "fullname": "1-simple_pagination.Server.DATA_FILE", "name": "DATA_FILE", "type": "builtins.str"}}, "__dataset": {".class": "SymbolTableNode", "implicit": true, "kind": "Mdef", "node": {".class": "Var", "flags": [], "fullname": "1-simple_pagination.Server.__dataset", "name": "__dataset", "type": {".class": "AnyType", "missing_import_name": null, "source_any": null, "type_of_any": 1}}}, "__init__": {".class": "SymbolTableNode", "kind": "Mdef", "node": {".class": "FuncDef", "arg_kinds": [0], "arg_names": ["self"], "flags": [], "fullname": "1-simple_pagination.Server.__init__", "name": "__init__", "type": null}}, "dataset": {".class": "SymbolTableNode", "kind": "Mdef", "node": {".class": "FuncDef", "arg_kinds": [0], "arg_names": ["self"], "flags": [], "fullname": "1-simple_pagination.Server.dataset", "name": "dataset", "type": {".class": "CallableType", "arg_kinds": [0], "arg_names": ["self"], "arg_types": ["1-simple_pagination.Server"], "bound_args": [], "def_extras": {"first_arg": "self"}, "fallback": "builtins.function", "implicit": false, "is_ellipsis_args": false, "name": "dataset of Server", "ret_type": {".class": "Instance", "args": [{".class": "Instance", "args": [{".class": "AnyType", "missing_import_name": null, "source_any": null, "type_of_any": 4}], "type_ref": "builtins.list"}], "type_ref": "builtins.list"}, "variables": []}}}, "get_page": {".class": "SymbolTableNode", "kind": "Mdef", "node": {".class": "FuncDef", "arg_kinds": [0, 1, 1], "arg_names": ["self", "page", "page_size"], "flags": [], "fullname": "1-simple_pagination.Server.get_page", "name": "get_page", "type": {".class": "CallableType", "arg_kinds": [0, 1, 1], "arg_names": ["self", "page", "page_size"], "arg_types": ["1-simple_pagination.Server", "builtins.int", "builtins.int"], "bound_args": [], "def_extras": {"first_arg": "self"}, "fallback": "builtins.function", "implicit": false, "is_ellipsis_args": false, "name": "get_page of Server", "ret_type": {".class": "Instance", "args": [{".class": "Instance", "args": [{".class": "AnyType", "missing_import_name": null, "source_any": null, "type_of_any": 4}], "type_ref": "builtins.list"}], "type_ref": "builtins.list"}, "variables": []}}}}, "tuple_type": null, "type_vars": [], "typeddict_type": null}}, "Tuple": {".class": "SymbolTableNode", "cross_ref": "typing.Tuple", "kind": "Gdef"}, "__doc__": {".class": "SymbolTableNode", "kind": "Gdef", "node": {".class": "Var", "flags": ["is_ready"], "fullname": "1-simple_pagination.__doc__", "name": "__doc__", "type": "builtins.str"}}, "__file__": {".class": "SymbolTableNode", "kind": "Gdef", "node": {".class": "Var", "flags": ["is_ready"], "fullname": "1-simple_pagination.__file__", "name": "__file__", "type": "builtins.str"}}, "__name__": {".class": "SymbolTableNode", "kind": "Gdef", "node": {".class": "Var", "flags": ["is_ready"], "fullname": "1-simple_pagination.__name__", "name": "__name__", "type": "builtins.str"}}, "__package__": {".class": "SymbolTableNode", "kind": "Gdef", "node": {".class": "Var", "flags": ["is_ready"], "fullname": "1-simple_pagination.__package__", "name": "__package__", "type": "builtins.str"}}, "csv": {".class": "SymbolTableNode", "cross_ref": "csv", "kind": "Gdef"}, "index_range": {".class": "SymbolTableNode", "kind": "Gdef", "node": {".class": "FuncDef", "arg_kinds": [0, 0], "arg_names": ["page", "page_size"], "flags": [], "fullname": "1-simple_pagination.index_range", "name": "index_range", "type": {".class": "CallableType", "arg_kinds": [0, 0], "arg_names": ["page", "page_size"], "arg_types": ["builtins.int", "builtins.int"], "bound_args": [], "def_extras": {"first_arg": null}, "fallback": "builtins.function", "implicit": false, "is_ellipsis_args": false, "name": "index_range", "ret_type": {".class": "TupleType", "implicit": false, "items": ["builtins.int", "builtins.int"], "partial_fallback": {".class": "Instance", "args": [{".class": "AnyType", "missing_import_name": null, "source_any": null, "type_of_any": 6}], "type_ref": "builtins.tuple"}}, "variables": []}}}, "math": {".class": "SymbolTableNode", "cross_ref": "math", "kind": "Gdef"}}, "path": "1-simple_pagination.py"}